[{"C:\\Users\\lenovo\\AppData\\Roaming\\Sublime Text 3\\.git\\COMMIT_EDITMSG": "ASCII"}, {"Z:\\cpp\\.git\\COMMIT_EDITMSG": "ASCII"}, {"Z:\\cpp\\Hesitage\\H_l2\\Makefile": "ASCII"}, {"Z:\\cpp\\Hesitage\\H_l2\\worker.cpp": "ASCII"}, {"Z:\\cpp\\Hesitage\\H_l2\\person.h": "ASCII"}, {"Z:\\cpp\\Hesitage\\H_l2\\person.cpp": "ASCII"}, {"Z:\\cpp\\Hesitage\\H_l2\\demo.cpp": "ASCII"}, {"Z:\\cpp\\Hesitage\\H_l2\\worker.h": "ASCII"}, {"E:\\GitHub\\gitignore\\C++.gitignore": "ASCII"}, {"Z:\\cpp\\.gitignore": "ASCII"}, {"Z:\\cpp\\Hesitage\\H_l1\\worker.cpp": "ASCII"}, {"Z:\\cpp\\Hesitage\\H_l1\\worker.h": "ASCII"}, {"Z:\\cpp\\Hesitage\\H_l1\\person.h": "ASCII"}, {"Z:\\cpp\\Hesitage\\H_l1\\person.cpp": "ASCII"}, {"Z:\\cpp\\Hesitage\\H_l1\\Makefile": "ASCII"}, {"Z:\\cpp\\Hesitage\\H_l1\\demo.cpp": "ASCII"}, {"C:\\Users\\lenovo\\.gitconfig": "ASCII"}, {"C:\\Users\\lenovo\\.bashrc": "ASCII"}, {"E:\\GitHub\\npp.sh": "ASCII"}, {"Z:\\cpp\\maze\\Readme.txt": "UTF-8"}, {"Z:\\cpp\\les6\\memory.cpp": "UTF-8"}, {"Z:\\cpp\\les7\\classdemo.cpp": "UTF-8"}, {"Z:\\cpp\\les9\\package.cpp": "ASCII"}, {"C:\\Users\\lenovo\\AppData\\Roaming\\Sublime Text 3\\Packages\\User\\Preferences.sublime-settings": "ASCII"}]